LICENSE
README.md
pyproject.toml
setup.py
src/file_reroute/__init__.py
src/file_reroute/reroute.py
src/file_reroute.egg-info/PKG-INFO
src/file_reroute.egg-info/SOURCES.txt
src/file_reroute.egg-info/dependency_links.txt
src/file_reroute.egg-info/requires.txt
src/file_reroute.egg-info/top_level.txt
tests/test_import.py