Metadata-Version: 2.1
Name: file-reroute
Version: 0.1.0
Summary: file rerouting package that makes it easy to run python code for both
Author: RonaldsonBellande
Author-email: ronaldsonbellande@gmail.com
Maintainer: RonaldsonBellande
Maintainer-email: ronaldsonbellande@gmail.com
License:                     GNU GENERAL PUBLIC LICENSE
Project-URL: Home, https://github.com/RonaldsonBellande/file-reroute
Project-URL: Homepage, https://github.com/RonaldsonBellande/file-reroute
Project-URL: documentation, https://github.com/RonaldsonBellande/file-reroute
Project-URL: repository, https://github.com/RonaldsonBellande/file-reroute
Keywords: package,setuptools
Classifier: License :: OSI Approved :: GNU General Public License v3 (GPLv3)
Classifier: Programming Language :: Python
Requires-Python: >=3.0
Provides-Extra: dev
License-File: LICENSE
